montecarlodata/__init__.py
montecarlodata/cli.py
montecarlodata/config.py
montecarlodata/errors.py
montecarlodata/fs_utils.py
montecarlodata/settings.py
montecarlodata/tools.py
montecarlodata/utils.py
montecarlodata/agents/__init__.py
montecarlodata/agents/agent.py
montecarlodata/agents/commands.py
montecarlodata/agents/fields.py
montecarlodata/collector/__init__.py
montecarlodata/collector/commands.py
montecarlodata/collector/fields.py
montecarlodata/collector/management.py
montecarlodata/collector/network_tests.py
montecarlodata/collector/validation.py
montecarlodata/common/__init__.py
montecarlodata/common/commands.py
montecarlodata/common/common.py
montecarlodata/common/data.py
montecarlodata/common/echo_utils.py
montecarlodata/common/resources.py
montecarlodata/common/user.py
montecarlodata/data_exports/__init__.py
montecarlodata/data_exports/catalog.py
montecarlodata/data_exports/commands.py
montecarlodata/data_exports/data_exports.py
montecarlodata/data_exports/fields.py
montecarlodata/dataimport/__init__.py
montecarlodata/dataimport/commands.py
montecarlodata/dataimport/dbt/__init__.py
montecarlodata/dataimport/dbt/service.py
montecarlodata/discovery/__init__.py
montecarlodata/discovery/commands.py
montecarlodata/discovery/networking.py
montecarlodata/discovery/policy_gen.py
montecarlodata/iac/__init__.py
montecarlodata/iac/client.py
montecarlodata/iac/commands.py
montecarlodata/iac/mc_config_service.py
montecarlodata/iac/schemas.py
montecarlodata/iac/utils.py
montecarlodata/insights/__init__.py
montecarlodata/insights/commands.py
montecarlodata/insights/data_insights.py
montecarlodata/insights/fields.py
montecarlodata/integrations/__init__.py
montecarlodata/integrations/commands.py
montecarlodata/integrations/keys.py
montecarlodata/integrations/configure/__init__.py
montecarlodata/integrations/configure/fields.py
montecarlodata/integrations/configure/bi/__init__.py
montecarlodata/integrations/configure/bi/bi.py
montecarlodata/integrations/info/__init__.py
montecarlodata-0.155.0.dist-info/LICENSE
montecarlodata-0.155.0.dist-info/METADATA
montecarlodata-0.155.0.dist-info/WHEEL
montecarlodata-0.155.0.dist-info/entry_points.txt
montecarlodata-0.155.0.dist-info/top_level.txt
montecarlodata-0.155.0.dist-info/RECORD
