Metadata-Version: 2.1
Name: montecarlodata
Version: 0.155.0
Summary: Monte Carlo's CLI
Home-page: https://www.montecarlodata.com/
Author: Monte Carlo Data, Inc
Author-email: info@montecarlodata.com
License: Apache Software License (Apache 2.0)
Classifier: Development Status :: 3 - Alpha
Classifier: Intended Audience :: Developers
Classifier: Natural Language :: English
Classifier: Topic :: Software Development :: Build Tools
Classifier: License :: OSI Approved :: Apache Software License
Classifier: Programming Language :: Python :: 3.8
Classifier: Programming Language :: Python :: 3.9
Classifier: Programming Language :: Python :: 3.10
Classifier: Programming Language :: Python :: 3.11
Classifier: Programming Language :: Python :: 3.12
Requires-Python: >=3.8
License-File: LICENSE
Requires-Dist: boto3 (>=1.19.4)
Requires-Dist: click-config-file (==0.6.0)
Requires-Dist: click (>=8.1.3)
Requires-Dist: dataclasses-json (>=0.6.7)
Requires-Dist: Jinja2 (>=3.1.6)
Requires-Dist: pycarlo (<1.0.0,>=0.11.7)
Requires-Dist: python-box (>=6.0.0)
Requires-Dist: PyYAML (>=5.4.1)
Requires-Dist: questionary (==1.10.0)
Requires-Dist: requests (<=3.0.0,>=2.0.0)
Requires-Dist: retry (==0.9.2)
Requires-Dist: tabulate (>=0.8.7)
Requires-Dist: setuptools (>=72.2.0) ; python_version >= "3.12"
